cglcovalenseglobal/__init__.py
cglcovalenseglobal/app.py
cglcovalenseglobal/generate_map.py
cglcovalenseglobal/get_translate.py
cglcovalenseglobal/load_dataset.py
cglcovalenseglobal/locustfile.py
cglcovalenseglobal/middleware.py
cglcovalenseglobal/openai_config.py
cglcovalenseglobal/process.py
cglcovalenseglobal/read_json.py
cglcovalenseglobal/test.py
cglcovalenseglobal/themes.py
cglcovalenseglobal-0.0.3.dist-info/METADATA
cglcovalenseglobal-0.0.3.dist-info/WHEEL
cglcovalenseglobal-0.0.3.dist-info/top_level.txt
cglcovalenseglobal-0.0.3.dist-info/RECORD
