Metadata-Version: 2.1
Name: cglcovalenseglobal
Version: 0.0.3
Requires-Dist: aiohttp ==3.9.0
Requires-Dist: aiosignal ==1.3.1
Requires-Dist: aiosmtplib ==2.0.2
Requires-Dist: annotated-types ==0.6.0
Requires-Dist: anyio ==3.7.1
Requires-Dist: async-timeout ==4.0.3
Requires-Dist: attrs ==23.1.0
Requires-Dist: azure-ai-textanalytics ==5.3.0
Requires-Dist: azure-ai-translation-text ==1.0.0b1
Requires-Dist: azure-common ==1.1.28
Requires-Dist: azure-core ==1.30.1
Requires-Dist: Babel ==2.13.1
Requires-Dist: beautifulsoup4 ==4.12.2
Requires-Dist: blinker ==1.7.0
Requires-Dist: branca ==0.7.0
Requires-Dist: certifi ==2023.11.17
Requires-Dist: charset-normalizer ==3.3.2
Requires-Dist: click ==8.1.7
Requires-Dist: colorama ==0.4.6
Requires-Dist: contourpy ==1.2.0
Requires-Dist: cycler ==0.12.1
Requires-Dist: dataclasses-json ==0.6.2
Requires-Dist: dill ==0.3.7
Requires-Dist: distro ==1.8.0
Requires-Dist: dnspython ==2.4.2
Requires-Dist: docx2pdf ==0.1.8
Requires-Dist: docxcompose ==1.4.0
Requires-Dist: docxtpl ==0.16.7
Requires-Dist: email-validator ==2.1.0.post1
Requires-Dist: exceptiongroup ==1.2.0
Requires-Dist: fastapi ==0.104.1
Requires-Dist: fastapi-mail ==1.4.1
Requires-Dist: folium ==0.15.0
Requires-Dist: fonttools ==4.45.0
Requires-Dist: frozenlist ==1.4.0
Requires-Dist: greenlet ==3.0.1
Requires-Dist: h11 ==0.14.0
Requires-Dist: httpcore ==1.0.2
Requires-Dist: httpx ==0.25.1
Requires-Dist: idna ==3.4
Requires-Dist: isodate ==0.6.1
Requires-Dist: Jinja2 ==3.1.2
Requires-Dist: joblib ==1.3.2
Requires-Dist: jsonpatch ==1.33
Requires-Dist: jsonpointer ==2.4
Requires-Dist: kiwisolver ==1.4.5
Requires-Dist: langchain ==0.0.339
Requires-Dist: langsmith ==0.0.66
Requires-Dist: lxml ==4.9.3
Requires-Dist: markdown-it-py ==3.0.0
Requires-Dist: MarkupSafe ==2.1.3
Requires-Dist: marshmallow ==3.20.1
Requires-Dist: mdurl ==0.1.2
Requires-Dist: msrest ==0.7.1
Requires-Dist: multidict ==6.0.4
Requires-Dist: mypy-extensions ==1.0.0
Requires-Dist: nltk ==3.8.1
Requires-Dist: numpy ==1.24.4
Requires-Dist: oauthlib ==3.2.2
Requires-Dist: openai ==1.5.0
Requires-Dist: packaging ==23.2
Requires-Dist: pandarallel ==1.6.5
Requires-Dist: pandas ==2.0.3
Requires-Dist: Pillow ==10.1.0
Requires-Dist: plotly ==5.18.0
Requires-Dist: psutil ==5.9.6
Requires-Dist: psycopg2-binary ==2.9.9
Requires-Dist: pydantic ==2.5.1
Requires-Dist: pydantic-settings ==2.1.0
Requires-Dist: pydantic-core ==2.14.3
Requires-Dist: Pygments ==2.17.2
Requires-Dist: pymessenger ==0.0.7.0
Requires-Dist: pyparsing ==3.1.1
Requires-Dist: pytesseract ==0.3.10
Requires-Dist: python-dateutil ==2.8.2
Requires-Dist: python-docx ==1.1.0
Requires-Dist: python-dotenv ==1.0.0
Requires-Dist: python-multipart ==0.0.6
Requires-Dist: pytz ==2023.3.post1
Requires-Dist: PyYAML ==6.0.1
Requires-Dist: regex ==2023.10.3
Requires-Dist: requests ==2.31.0
Requires-Dist: requests-oauthlib ==1.4.0
Requires-Dist: requests-toolbelt ==1.0.0
Requires-Dist: rich ==13.7.0
Requires-Dist: scikit-learn ==1.3.2
Requires-Dist: scipy ==1.10.1
Requires-Dist: six ==1.16.0
Requires-Dist: sniffio ==1.3.0
Requires-Dist: soupsieve ==2.5
Requires-Dist: sqladmin ==0.16.0
Requires-Dist: SQLAlchemy ==2.0.23
Requires-Dist: starlette ==0.27.0
Requires-Dist: tenacity ==8.2.3
Requires-Dist: threadpoolctl ==3.2.0
Requires-Dist: tiktoken ==0.5.1
Requires-Dist: tqdm ==4.66.1
Requires-Dist: typing-inspect ==0.9.0
Requires-Dist: typing-extensions ==4.8.0
Requires-Dist: tzdata ==2023.3
Requires-Dist: urllib3 ==2.1.0
Requires-Dist: uvicorn ==0.24.0.post1
Requires-Dist: WTForms ==3.1.1
Requires-Dist: yarl ==1.9.3
